setup.py
simple_matrix/MatrixImplementation.py
simple_matrix/__init__.py
simple_matrix.egg-info/PKG-INFO
simple_matrix.egg-info/SOURCES.txt
simple_matrix.egg-info/dependency_links.txt
simple_matrix.egg-info/top_level.txt