Metadata-Version: 1.0
Name: simple-matrix
Version: 1.0
Summary: Implements some matrix operations
Home-page: UNKNOWN
Author: UNKNOWN
Author-email: UNKNOWN
License: UNKNOWN
Platform: UNKNOWN
